sdl2/SDL2.dll
sdl2/SDL2_image.dll
sdl2/SDL2_mixer.dll
sdl2/SDL2_ttf.dll
sdl2/__init__.py
sdl2/_cffi.py
sdl2/_gl.pyd
sdl2/_sdl2.pyd
sdl2/gl.py
sdl2/gl.xml
sdl2/gl_api.py
sdl2/libFLAC-8.dll
sdl2/libfreetype-6.dll
sdl2/libjpeg-9.dll
sdl2/libmikmod-2.dll
sdl2/libmodplug-1.dll
sdl2/libogg-0.dll
sdl2/libpng16-16.dll
sdl2/libtiff-5.dll
sdl2/libvorbis-0.dll
sdl2/libvorbisfile-3.dll
sdl2/libwebp-4.dll
sdl2/sdl2.py
sdl2/smpeg2.dll
sdl2/zlib1.dll
sdl2_cffi-1.0.6.dist-info/DESCRIPTION.rst
sdl2_cffi-1.0.6.dist-info/METADATA
sdl2_cffi-1.0.6.dist-info/RECORD
sdl2_cffi-1.0.6.dist-info/WHEEL
sdl2_cffi-1.0.6.dist-info/metadata.json
sdl2_cffi-1.0.6.dist-info/top_level.txt
