Metadata-Version: 2.0
Name: sdl2-cffi
Version: 1.0.6
Summary: CFFI wrapper for SDL2
Home-page: https://github.com/kahowell/sdl2-cffi
Author: Kevin Howell
Author-email: kevin@kahowell.net
License: UNKNOWN
Keywords: sdl2,cffi
Platform: UNKNOWN
Classifier: Development Status :: 3 - Alpha
Classifier: License :: OSI Approved :: zlib/libpng License
Classifier: Programming Language :: Python :: 2.7
Classifier: Programming Language :: Python :: 3
Classifier: Programming Language :: Python :: 3.4
Classifier: Programming Language :: Python :: Implementation :: CPython
Classifier: Programming Language :: Python :: Implementation :: PyPy
Requires-Dist: cffi (>=1.0.0)
